{
  "collections": [
    {
      "collection": "goods_receipt_items",
      "meta": {
        "collection": "goods_receipt_items",
        "icon": "format_list_bulleted",
        "note": "รายการสินค้าในใบรับสินค้า",
        "display_template": "{{product_name}} x {{received_quantity}}",
        "hidden": false,
        "singleton": false,
        "translations": null,
        "archive_field": null,
        "archive_app_filter": true,
        "archive_value": null,
        "unarchive_value": null,
        "sort_field": "line_number",
        "accountability": "all",
        "color": "#8BC34A",
        "item_duplication_fields": null,
        "sort": 12,
        "group": "Procurement",
        "collapse": "open"
      },
      "schema": {}
    }
  ],
  "fields": [
    {
      "collection": "goods_receipt_items",
      "field": "id",
      "type": "integer",
      "schema": {
        "name": "id",
        "table": "goods_receipt_items",
        "data_type": "int unsigned",
        "is_nullable": false,
        "is_primary_key": true,
        "has_auto_increment": true
      },
      "meta": {
        "collection": "goods_receipt_items",
        "field": "id",
        "interface": "input",
        "readonly": true,
        "hidden": true,
        "sort": 1,
        "width": "full"
      }
    },
    {
      "collection": "goods_receipt_items",
      "field": "gr_id",
      "type": "integer",
      "schema": {
        "name": "gr_id",
        "table": "goods_receipt_items",
        "data_type": "int unsigned",
        "is_nullable": false,
        "foreign_key_table": "goods_receipts",
        "foreign_key_column": "id"
      },
      "meta": {
        "collection": "goods_receipt_items",
        "field": "gr_id",
        "special": ["m2o"]
      }
    },
    {
      "collection": "goods_receipt_items",
      "field": "product_name",
      "type": "string",
      "schema": {
        "name": "product_name",
        "table": "goods_receipt_items",
        "data_type": "varchar",
        "max_length": 255,
        "is_nullable": false
      },
      "meta": {
        "collection": "goods_receipt_items",
        "field": "product_name",
        "interface": "input",
        "options": {
          "placeholder": "ชื่อสินค้า"
        },
        "sort": 2,
        "width": "half",
        "note": "ชื่อสินค้า",
        "required": true
      }
    },
    {
      "collection": "goods_receipt_items",
      "field": "received_quantity",
      "type": "decimal",
      "schema": {
        "name": "received_quantity",
        "table": "goods_receipt_items",
        "data_type": "decimal",
        "numeric_precision": 10,
        "numeric_scale": 2,
        "is_nullable": false
      },
      "meta": {
        "collection": "goods_receipt_items",
        "field": "received_quantity",
        "interface": "input",
        "options": {
          "placeholder": "จำนวนที่รับ"
        },
        "sort": 3,
        "width": "half",
        "note": "จำนวนที่รับ",
        "required": true
      }
    },
    {
      "collection": "goods_receipt_items",
      "field": "unit_price",
      "type": "decimal",
      "schema": {
        "name": "unit_price",
        "table": "goods_receipt_items",
        "data_type": "decimal",
        "numeric_precision": 10,
        "numeric_scale": 2,
        "is_nullable": false
      },
      "meta": {
        "collection": "goods_receipt_items",
        "field": "unit_price",
        "interface": "input",
        "options": {
          "placeholder": "ราคาต่อหน่วย"
        },
        "sort": 4,
        "width": "half",
        "note": "ราคาต่อหน่วย",
        "required": true
      }
    },
    {
      "collection": "goods_receipt_items",
      "field": "total_price",
      "type": "decimal",
      "schema": {
        "name": "total_price",
        "table": "goods_receipt_items",
        "data_type": "decimal",
        "numeric_precision": 10,
        "numeric_scale": 2,
        "is_nullable": false
      },
      "meta": {
        "collection": "goods_receipt_items",
        "field": "total_price",
        "interface": "input",
        "display": "formatted-value",
        "display_options": {
          "format": true,
          "currency": "THB"
        },
        "readonly": true,
        "sort": 5,
        "width": "half",
        "note": "ราคารวม",
        "required": true
      }
    },
    {
      "collection": "goods_receipt_items",
      "field": "line_number",
      "type": "integer",
      "schema": {
        "name": "line_number",
        "table": "goods_receipt_items",
        "data_type": "int unsigned",
        "is_nullable": false
      },
      "meta": {
        "collection": "goods_receipt_items",
        "field": "line_number",
        "interface": "input",
        "readonly": true,
        "hidden": true,
        "sort": 6,
        "width": "half",
        "note": "หมายเลขบรรทัด"
      }
    },
    {
      "collection": "goods_receipt_items",
      "field": "remarks",
      "type": "text",
      "schema": {
        "name": "remarks",
        "table": "goods_receipt_items",
        "data_type": "text",
        "is_nullable": true
      },
      "meta": {
        "collection": "goods_receipt_items",
        "field": "remarks",
        "interface": "textarea",
        "options": {
          "placeholder": "หมายเหตุเพิ่มเติม"
        },
        "sort": 7,
        "width": "full",
        "note": "หมายเหตุ"
      }
    }
  ]
} 